tracardi_plugin_sdk/__init__.py
tracardi_plugin_sdk/action_runner.py
tracardi_plugin_sdk/domain/__init__.py
tracardi_plugin_sdk/domain/console.py
tracardi_plugin_sdk/domain/register.py
tracardi_plugin_sdk/domain/result.py
tracardi_plugin_sdk/domain/__pycache__/__init__.cpython-37.pyc
tracardi_plugin_sdk/domain/__pycache__/__init__.cpython-38.pyc
tracardi_plugin_sdk/domain/__pycache__/console.cpython-37.pyc
tracardi_plugin_sdk/domain/__pycache__/console.cpython-38.pyc
tracardi_plugin_sdk/domain/__pycache__/register.cpython-37.pyc
tracardi_plugin_sdk/domain/__pycache__/register.cpython-38.pyc
tracardi_plugin_sdk/domain/__pycache__/result.cpython-37.pyc
tracardi_plugin_sdk/domain/__pycache__/result.cpython-38.pyc
tracardi_plugin_sdk/service/__init__.py
tracardi_plugin_sdk/service/plugin_runner.py
tracardi_plugin_sdk/service/__pycache__/__init__.cpython-38.pyc
tracardi_plugin_sdk/service/__pycache__/plugin_runner.cpython-37.pyc
tracardi_plugin_sdk/service/__pycache__/plugin_runner.cpython-38.pyc
tracardi_plugin_sdk-0.6.31.dist-info/METADATA
tracardi_plugin_sdk-0.6.31.dist-info/WHEEL
tracardi_plugin_sdk-0.6.31.dist-info/top_level.txt
tracardi_plugin_sdk-0.6.31.dist-info/RECORD
