Metadata-Version: 2.1
Name: tracardi-plugin-sdk
Version: 0.6.31
Summary: Tracardi Plugin SDK
Home-page: UNKNOWN
Author: Risto Kowaczewski
Author-email: risto.kowaczewski@gmail.com
License: UNKNOWN
Platform: UNKNOWN
Classifier: Programming Language :: Python :: 3
Classifier: License :: OSI Approved :: MIT License
Classifier: Operating System :: OS Independent
Requires-Dist: pydantic (>=1.8.2)
Requires-Dist: tracardi-dot-notation (>=0.6.5)
